Yadro_test/fifo.sv
module fifo
# (
    parameter WIDTH = 32, DEPTH = 2
)
(
    input                clk,
    input                rst,
    input                push,
    input                pop,
    input  [WIDTH - 1:0] wr_data,
    output [WIDTH - 1:0] rd_data
    // output               empty,
    // output               full
);



    localparam PTR_WIDTH = $clog2(DEPTH);
    localparam max_ptr   = PTR_WIDTH' (DEPTH - 1);

    logic [WIDTH - 1:0]      data_arr [DEPTH - 1: 0];
    logic [PTR_WIDTH - 1: 0] write_ptr;
    logic [PTR_WIDTH - 1: 0] read_ptr;
    logic                    mod_2;

    // assign empty     = (write_ptr == read_ptr) & (~mod_2);
    // assign full      = (write_ptr == read_ptr) & (mod_2);
    assign rd_data = data_arr[read_ptr];

    always_ff @ (posedge clk or posedge rst)
        if (rst)
            write_ptr <= '0;
        else if (push)
            write_ptr <= write_ptr == max_ptr ? '0 : write_ptr + 1'b1;

    always_ff @ (posedge clk or posedge rst)
        if (rst)
            read_ptr <= '0;
        else if (pop)
            read_ptr <= read_ptr == max_ptr ? '0 : read_ptr + 1'b1;

    always_ff @ (posedge clk or posedge rst)
        if (rst)
            mod_2 <= '0;
        else 
            mod_2 <= mod_2 ^ (push & (write_ptr == max_ptr)) ^ (pop & (read_ptr == max_ptr));

    always_ff @ (posedge clk)
        if (push) 
            data_arr[write_ptr] <= wr_data;

endmodule

Yadro_test/reg_with_en.sv
module register_with_en
#(
    parameter WIDTH = 32
)
(
    input                      clk,
    input                      en,
    input        [WIDTH - 1:0] d,
    output logic [WIDTH - 1:0] q
);

    always_ff @ (posedge clk)
        if (en)
            q <= d;

endmodule

Yadro_test/reg_with_rst.sv
module register_with_rst
#(
    parameter WIDTH = 32
)
(
    input                      clk,
    input                      rst,
    input        [WIDTH - 1:0] d,
    output logic [WIDTH - 1:0] q
);

    always_ff @ (posedge clk)
        if (rst)
            q <= '0;
        else
            q <= d;

endmodule

Yadro_test/asr_1.sv
module asr_1
#(
    parameter ARG_WIDTH = 32,
    parameter RES_WIDTH = ARG_WIDTH
)
(
    input                           arg_vld,
    input  signed [ARG_WIDTH - 1:0] a,
    output                          res_vld,
    output signed [RES_WIDTH - 1:0] res
);

    assign res      = a >>> 1;
    assign res_vld  = arg_vld;
    
endmodule

Yadro_test/sub.sv
module sub
#(
    parameter ARG_WIDTH = 32,
    parameter RES_WIDTH = ARG_WIDTH + 1
)
(
    input                           arg_vld,
    input  signed [ARG_WIDTH - 1:0] a,
    input  signed [ARG_WIDTH - 1:0] b,
    output                          res_vld,
    output signed [RES_WIDTH - 1:0] res
);

    logic                       overflow;
    logic signed [ARG_WIDTH :0] tmp;

    assign tmp      = a - b;
    assign overflow = tmp[ARG_WIDTH] ^ tmp[ARG_WIDTH-1]; // !=
    assign res      = tmp[RES_WIDTH - 1:0];
    
    // alternative
    // assign res      = a - b;
    // assign overflow = (a[WIDTH - 1] ~^ b[WIDTH - 1]) && (res[WIDTH - 1] ^ a[WIDTH - 1]);

    assign res_vld  = arg_vld;
    
endmodule

Yadro_test/mul.sv
module mul
#(
    parameter ARG_WIDTH = 32,
    parameter RES_WIDTH = ARG_WIDTH * 2
)
(
    input                           arg_vld,
    input  signed [ARG_WIDTH - 1:0] a,
    input  signed [ARG_WIDTH - 1:0] b,
    output                          res_vld,
    output signed [RES_WIDTH - 1:0] res
);

    logic                              overflow;
    logic signed [ARG_WIDTH * 2 - 1:0] tmp;

    assign tmp      = a * b;
    assign overflow =(tmp != $signed(tmp[ARG_WIDTH-1:0]));
    assign res      = tmp[RES_WIDTH - 1:0];
    assign res_vld  = arg_vld;


endmodule

Yadro_test/add.sv
module add
#(
    parameter ARG_WIDTH = 32,
    parameter RES_WIDTH = ARG_WIDTH + 1
)
(
    input                           arg_vld,
    input  signed [ARG_WIDTH - 1:0] a,
    input  signed [ARG_WIDTH - 1:0] b,
    output                          res_vld,
    output signed [RES_WIDTH - 1:0] res
);

    logic                       overflow;
    logic signed [ARG_WIDTH :0] tmp;

    assign tmp      = a + b;
    assign overflow = tmp[ARG_WIDTH] ^ tmp[ARG_WIDTH-1]; // !=
    assign res      = tmp[RES_WIDTH - 1:0];
    assign res_vld  = arg_vld;
    
endmodule

Yadro_test/sl_2.sv
module sl_2
#(
    parameter ARG_WIDTH = 32,
    parameter RES_WIDTH = ARG_WIDTH
)
(
    input                           arg_vld,
    input  signed [ARG_WIDTH - 1:0] a,
    output                          res_vld,
    output signed [RES_WIDTH - 1:0] res
);

    logic                          overflow;
    logic signed [ARG_WIDTH + 1:0] tmp; // ARG_WIDTH + 2 bit for shift

    assign tmp      = a << 2;
    assign overflow = | tmp[ARG_WIDTH + 1 : ARG_WIDTH]; // !=
    assign res      = tmp[RES_WIDTH - 1:0];
    assign res_vld  = arg_vld;
    
endmodule

Yadro_test/yadro_equation.sv
module yadro_equation
#(
    parameter WIDTH = 32
)
(   
    input                        clk,
    input                        rst,
    input                        arg_vld,
    input  signed [WIDTH - 1: 0] a,
    input  signed [WIDTH - 1: 0] b,
    input  signed [WIDTH - 1: 0] c,
    input  signed [WIDTH - 1: 0] d,
    output                       res_vld,
    output signed [WIDTH - 1: 0] res
);

    localparam SUB1_RES_WIDTH = WIDTH;
    localparam MUL1_RES_WIDTH = WIDTH;
    localparam SL_RES_WIDTH   = WIDTH;
    localparam ADD_RES_WIDTH  = WIDTH;
    localparam MUL2_ARG_WIDTH = ADD_RES_WIDTH > SUB1_RES_WIDTH ? ADD_RES_WIDTH : SUB1_RES_WIDTH;
    localparam MUL2_RES_WIDTH = WIDTH;
    localparam SUB2_ARG_WIDTH = MUL2_RES_WIDTH > SL_RES_WIDTH ? MUL2_RES_WIDTH : SL_RES_WIDTH;
    localparam SUB2_RES_WIDTH = WIDTH;
    localparam ASR_RES_WIDTH  = WIDTH;


    logic [SUB1_RES_WIDTH - 1: 0] fifo1_rd;
    logic [SUB1_RES_WIDTH - 1: 0] fifo2_rd;


    logic                         sub1_res_vld;
    logic [SUB1_RES_WIDTH - 1: 0] sub1_res;

    sub #( .ARG_WIDTH(WIDTH), .RES_WIDTH(SUB1_RES_WIDTH) ) sub1 
    (
        .arg_vld (arg_vld     ),
        .a       (a           ),
        .b       (b           ),
        .res_vld (sub1_res_vld),
        .res     (sub1_res    )
    );

    logic                         mul1_res_vld;
    logic [MUL1_RES_WIDTH - 1: 0] mul1_res;

    mul #( .ARG_WIDTH(WIDTH), .RES_WIDTH(MUL1_RES_WIDTH) ) mul1 
    (
        .arg_vld (arg_vld     ),
        .a       (WIDTH'(3)  ), // 'sd3
        .b       (c           ),
        .res_vld (mul1_res_vld),
        .res     (mul1_res    )
    );

    logic                         sl_res_vld;
    logic [SL_RES_WIDTH   - 1: 0] sl_res;

    sl_2 #( .ARG_WIDTH(WIDTH), .RES_WIDTH(SL_RES_WIDTH) ) sl 
    (
        .arg_vld (arg_vld     ),
        .a       (d           ), 
        .res_vld (sl_res_vld  ),
        .res     (sl_res      )
    );


    logic                         mul1_out_vld;
    logic [MUL1_RES_WIDTH - 1: 0] mul1_out;
    register_with_rst #(.WIDTH(1))             r_1_vld  (clk, rst, mul1_res_vld, mul1_out_vld);
    register_with_en #(.WIDTH(MUL1_RES_WIDTH)) r_1_data (clk, mul1_res_vld, mul1_res, mul1_out);


    logic                         add_res_vld;
    logic [SUB1_RES_WIDTH - 1: 0] add_res;

    add #( .ARG_WIDTH(MUL1_RES_WIDTH), .RES_WIDTH(ADD_RES_WIDTH) ) add 
    (
        .arg_vld (mul1_out_vld),
        .a       (WIDTH'(1)  ), // 'sd1
        .b       (mul1_out    ),
        .res_vld (add_res_vld ),
        .res     (add_res     )
    );

    logic                         add_out_vld;
    logic [ADD_RES_WIDTH  - 1: 0] add_out;
    register_with_rst #(.WIDTH(1))            r_2_vld  (clk, rst, add_res_vld, add_out_vld);
    register_with_en #(.WIDTH(ADD_RES_WIDTH)) r_2_data (clk, add_res_vld, add_res, add_out);


    logic                         mul2_res_vld;
    logic [MUL2_RES_WIDTH - 1: 0] mul2_res;

    mul #( .ARG_WIDTH(MUL2_ARG_WIDTH), .RES_WIDTH(MUL2_RES_WIDTH) ) mul2  
    (
        .arg_vld (add_out_vld ),
        .a       (fifo1_rd    ), // 'sd3
        .b       (add_out     ),
        .res_vld (mul2_res_vld),
        .res     (mul2_res    )
    );


    logic                         mul2_out_vld;
    logic [MUL2_RES_WIDTH - 1: 0] mul2_out;
    register_with_rst #(.WIDTH(1))             r_3_vld  (clk, rst, mul2_res_vld, mul2_out_vld);
    register_with_en #(.WIDTH(MUL2_RES_WIDTH)) r_3_data (clk, mul2_res_vld, mul2_res, mul2_out);

    logic                         sub2_res_vld;
    logic [SUB2_RES_WIDTH - 1: 0] sub2_res;

    sub #( .ARG_WIDTH(SUB2_ARG_WIDTH), .RES_WIDTH(SUB2_RES_WIDTH) ) sub2 
    (
        .arg_vld (mul2_out_vld),
        .a       (mul2_out    ),
        .b       (fifo2_rd    ),
        .res_vld (sub2_res_vld),
        .res     (sub2_res    )
    );

    logic                         asr_res_vld;
    logic [SL_RES_WIDTH   - 1: 0] asr_res;

    asr_1 #( .ARG_WIDTH(SUB2_RES_WIDTH), .RES_WIDTH(ASR_RES_WIDTH) ) asr
    (
        .arg_vld (sub2_res_vld),
        .a       (sub2_res    ), 
        .res_vld (asr_res_vld ),
        .res     (asr_res     )
    );

    logic                         asr_out_vld;
    logic [ASR_RES_WIDTH - 1: 0]  asr_out;
    register_with_rst #(.WIDTH(1))            r_4_vld  (clk, rst, asr_res_vld, asr_out_vld);
    register_with_en #(.WIDTH(ASR_RES_WIDTH)) r_4_data (clk, asr_res_vld, asr_res, asr_out);

    fifo #( .WIDTH(SUB1_RES_WIDTH), .DEPTH(2)) fifo1
    (
        .clk     (clk         ),
        .rst     (rst         ),
        .push    (sub1_res_vld),
        .pop     (add_out_vld ),
        .wr_data (sub1_res    ),
        .rd_data (fifo1_rd    )
    );

    fifo #( .WIDTH(SUB1_RES_WIDTH), .DEPTH(3)) fifo2
    (
        .clk     (clk         ),
        .rst     (rst         ),
        .push    (sl_res_vld  ),
        .pop     (mul2_out_vld),
        .wr_data (sl_res      ),
        .rd_data (fifo2_rd    )
    );

    assign res_vld = asr_out_vld;
    assign res     = asr_out;
    
endmodule

Yadro_test/tb.sv
module tb;

    localparam WIDTH = 32;

    logic                clk;
    logic                rst;

    logic                arg_vld;
    logic  signed [WIDTH - 1:0] a, b, c, d;

    logic  signed               res_vld;
    logic  signed [WIDTH - 1:0] res;

    logic  signed [WIDTH - 1:0] res_expected;

    yadro_equation #(.WIDTH(WIDTH)) dut (.*);
    
    initial
    begin
        clk = '1;

        forever
        begin
            # 5
            clk = ~ clk;
        end
    end

    task reset ();

        rst <= 'x;
        repeat (3) @ (posedge clk);
        rst <= '1;
        repeat (3) @ (posedge clk);
        rst <= '0;

    endtask

    int test_num = 0;
    int file_in;
    int errors = 0;
    int args_cnt;

    logic  signed [WIDTH - 1:0] a_tmp, b_tmp, c_tmp, d_tmp;
    logic  signed [WIDTH - 1:0] res_expected_tmp;

    initial begin
        arg_vld <= '0;
        reset ();
        
        file_in = $fopen("test_vectors.txt", "r");
        if (!file_in) begin
            $display("Error: Cannot open file 'test_vectors.txt'!");
            $finish;
        end

        while (!$feof(file_in)) begin
            // $display("Test #%d", test_num);
            test_num++;
            args_cnt = $fscanf(file_in, "%d %d %d %d %d", a_tmp, b_tmp, c_tmp, d_tmp, res_expected_tmp);
            if (args_cnt != 5) begin
                $display("Error fscanf #args: %3d (expected %3d)", args_cnt, 5);
                // $finish;
            end
            else begin
            a       <= a_tmp;
            b       <= b_tmp;
            c       <= c_tmp;
            d       <= d_tmp;
            arg_vld <= '1;

            res_expected <= res_expected_tmp;

            @ (posedge clk);
            arg_vld <= '0;
            end 
        end

        $fclose(file_in);
        $display("Tests completed. Errors: %0d", errors);

        repeat (3) @ (posedge clk);
        $finish;
    end

    //-------------------------------------------------------------------------

    int cycle = 0;

    always @ (posedge clk)
    begin
        $write (" cycle  %5d --", cycle);
        cycle <= cycle + 1'b1;

        if (rst)
            $write (" rst");
        else
            $write ("    ");

        if (arg_vld)
            $write (" arg %12d %12d %12d %12d", a, b, c, d);
        else
            $write ("                                     ");

        if (res_vld)
            $write (" res %12d", res);

        $display;
    end
    //-------------------------------------------------------------------------
    logic [WIDTH - 1:0] queue [$];

    logic was_reset = 0;

    always @ (posedge clk)
    begin
        if (rst)
        begin
            queue = {};
            was_reset = 1;
        end
        else if (was_reset)
        begin
            if (arg_vld)
            begin
                queue.push_back (res_expected);
                // $display (" push_back: expected result %0d", res_expected);
            end

            if (res_vld)
            begin
                if (queue.size () == 0)
                begin
                    $display (" FAIL: unexpected result %0d", res);
                    // $finish;
                end
                else
                begin
                    // `ifdef __ICARUS__
                        // Some version of Icarus has a bug, and this is a workaround
                        // res_expected = queue [0];
                        // queue.delete (0);
                    // `else
                        res_expected = queue.pop_front ();
                    // `endif

                    if (res !== res_expected)
                    begin
                        $display (" FAIL: res mismatch. Expected %0d, actual %0d",
                            res_expected, res);
                        // $finish;
                    end
                end
            end
        end
    end


    initial begin
        $dumpfile ("dump.vcd");
        $dumpvars ();
        #1;
    end

    initial
    begin
        repeat (1000) @ (posedge clk);
        $display ("TIMEOUT REACHED!");
        $finish;
    end


endmodule

Yadro_test/dump.vcd
$date
	Tue May 06 17:10:48 2025
$end
$version
	Icarus Verilog
$end
$timescale
	1s
$end
$scope module tb $end
$var wire 1 ! res_vld $end
$var wire 32 " res [31:0] $end
$var parameter 32 # WIDTH $end
$var reg 32 $ a [31:0] $end
$var reg 32 % a_tmp [31:0] $end
$var reg 1 & arg_vld $end
$var reg 32 ' b [31:0] $end
$var reg 32 ( b_tmp [31:0] $end
$var reg 32 ) c [31:0] $end
$var reg 32 * c_tmp [31:0] $end
$var reg 1 + clk $end
$var reg 32 , d [31:0] $end
$var reg 32 - d_tmp [31:0] $end
$var reg 32 . res_expected [31:0] $end
$var reg 32 / res_expected_tmp [31:0] $end
$var reg 1 0 rst $end
$var reg 1 1 was_reset $end
$var integer 32 2 args_cnt [31:0] $end
$var integer 32 3 cycle [31:0] $end
$var integer 32 4 errors [31:0] $end
$var integer 32 5 file_in [31:0] $end
$var integer 32 6 test_num [31:0] $end
$scope module dut $end
$var wire 32 7 a [31:0] $end
$var wire 1 & arg_vld $end
$var wire 32 8 b [31:0] $end
$var wire 32 9 c [31:0] $end
$var wire 1 + clk $end
$var wire 32 : d [31:0] $end
$var wire 32 ; res [31:0] $end
$var wire 1 ! res_vld $end
$var wire 1 0 rst $end
$var wire 1 < sub2_res_vld $end
$var wire 32 = sub2_res [31:0] $end
$var wire 1 > sub1_res_vld $end
$var wire 32 ? sub1_res [31:0] $end
$var wire 1 @ sl_res_vld $end
$var wire 32 A sl_res [31:0] $end
$var wire 1 B mul2_res_vld $end
$var wire 32 C mul2_res [31:0] $end
$var wire 1 D mul2_out_vld $end
$var wire 32 E mul2_out [31:0] $end
$var wire 1 F mul1_res_vld $end
$var wire 32 G mul1_res [31:0] $end
$var wire 1 H mul1_out_vld $end
$var wire 32 I mul1_out [31:0] $end
$var wire 32 J fifo2_rd [31:0] $end
$var wire 32 K fifo1_rd [31:0] $end
$var wire 1 L asr_res_vld $end
$var wire 32 M asr_res [31:0] $end
$var wire 1 N asr_out_vld $end
$var wire 32 O asr_out [31:0] $end
$var wire 1 P add_res_vld $end
$var wire 32 Q add_res [31:0] $end
$var wire 1 R add_out_vld $end
$var wire 32 S add_out [31:0] $end
$var parameter 32 T ADD_RES_WIDTH $end
$var parameter 32 U ASR_RES_WIDTH $end
$var parameter 32 V MUL1_RES_WIDTH $end
$var parameter 32 W MUL2_ARG_WIDTH $end
$var parameter 32 X MUL2_RES_WIDTH $end
$var parameter 32 Y SL_RES_WIDTH $end
$var parameter 32 Z SUB1_RES_WIDTH $end
$var parameter 32 [ SUB2_ARG_WIDTH $end
$var parameter 32 \ SUB2_RES_WIDTH $end
$var parameter 32 ] WIDTH $end
$scope module add $end
$var wire 32 ^ a [31:0] $end
$var wire 1 _ overflow $end
$var wire 1 P res_vld $end
$var wire 33 ` tmp [32:0] $end
$var wire 32 a res [31:0] $end
$var wire 32 b b [31:0] $end
$var wire 1 H arg_vld $end
$var parameter 32 c ARG_WIDTH $end
$var parameter 32 d RES_WIDTH $end
$upscope $end
$scope module asr $end
$var wire 1 L res_vld $end
$var wire 32 e res [31:0] $end
$var wire 1 < arg_vld $end
$var wire 32 f a [31:0] $end
$var parameter 32 g ARG_WIDTH $end
$var parameter 32 h RES_WIDTH $end
$upscope $end
$scope module fifo1 $end
$var wire 1 + clk $end
$var wire 32 i rd_data [31:0] $end
$var wire 1 0 rst $end
$var wire 32 j wr_data [31:0] $end
$var wire 1 > push $end
$var wire 1 R pop $end
$var parameter 32 k DEPTH $end
$var parameter 32 l PTR_WIDTH $end
$var parameter 32 m WIDTH $end
$var parameter 1 n max_ptr $end
$var reg 1 o mod_2 $end
$var reg 1 p read_ptr $end
$var reg 1 q write_ptr $end
$upscope $end
$scope module fifo2 $end
$var wire 1 + clk $end
$var wire 32 r rd_data [31:0] $end
$var wire 1 0 rst $end
$var wire 32 s wr_data [31:0] $end
$var wire 1 @ push $end
$var wire 1 D pop $end
$var parameter 32 t DEPTH $end
$var parameter 32 u PTR_WIDTH $end
$var parameter 32 v WIDTH $end
$var parameter 2 w max_ptr $end
$var reg 1 x mod_2 $end
$var reg 2 y read_ptr [1:0] $end
$var reg 2 z write_ptr [1:0] $end
$upscope $end
$scope module mul1 $end
$var wire 32 { a [31:0] $end
$var wire 1 & arg_vld $end
$var wire 32 | b [31:0] $end
$var wire 1 F res_vld $end
$var wire 64 } tmp [63:0] $end
$var wire 32 ~ res [31:0] $end
$var wire 1 !" overflow $end
$var parameter 32 "" ARG_WIDTH $end
$var parameter 32 #" RES_WIDTH $end
$upscope $end
$scope module mul2 $end
$var wire 32 $" a [31:0] $end
$var wire 1 B res_vld $end
$var wire 64 %" tmp [63:0] $end
$var wire 32 &" res [31:0] $end
$var wire 1 '" overflow $end
$var wire 32 (" b [31:0] $end
$var wire 1 R arg_vld $end
$var parameter 32 )" ARG_WIDTH $end
$var parameter 32 *" RES_WIDTH $end
$upscope $end
$scope module r_1_data $end
$var wire 1 + clk $end
$var wire 32 +" d [31:0] $end
$var wire 1 F en $end
$var parameter 32 ," WIDTH $end
$var reg 32 -" q [31:0] $end
$upscope $end
$scope module r_1_vld $end
$var wire 1 + clk $end
$var wire 1 F d $end
$var wire 1 0 rst $end
$var parameter 32 ." WIDTH $end
$var reg 1 H q $end
$upscope $end
$scope module r_2_data $end
$var wire 1 + clk $end
$var wire 32 /" d [31:0] $end
$var wire 1 P en $end
$var parameter 32 0" WIDTH $end
$var reg 32 1" q [31:0] $end
$upscope $end
$scope module r_2_vld $end
$var wire 1 + clk $end
$var wire 1 P d $end
$var wire 1 0 rst $end
$var parameter 32 2" WIDTH $end
$var reg 1 R q $end
$upscope $end
$scope module r_3_data $end
$var wire 1 + clk $end
$var wire 32 3" d [31:0] $end
$var wire 1 B en $end
$var parameter 32 4" WIDTH $end
$var reg 32 5" q [31:0] $end
$upscope $end
$scope module r_3_vld $end
$var wire 1 + clk $end
$var wire 1 B d $end
$var wire 1 0 rst $end
$var parameter 32 6" WIDTH $end
$var reg 1 D q $end
$upscope $end
$scope module r_4_data $end
$var wire 1 + clk $end
$var wire 32 7" d [31:0] $end
$var wire 1 L en $end
$var parameter 32 8" WIDTH $end
$var reg 32 9" q [31:0] $end
$upscope $end
$scope module r_4_vld $end
$var wire 1 + clk $end
$var wire 1 L d $end
$var wire 1 0 rst $end
$var parameter 32 :" WIDTH $end
$var reg 1 N q $end
$upscope $end
$scope module sl $end
$var wire 32 ;" a [31:0] $end
$var wire 1 & arg_vld $end
$var wire 1 @ res_vld $end
$var wire 34 <" tmp [33:0] $end
$var wire 32 =" res [31:0] $end
$var wire 1 >" overflow $end
$var parameter 32 ?" ARG_WIDTH $end
$var parameter 32 @" RES_WIDTH $end
$upscope $end
$scope module sub1 $end
$var wire 32 A" a [31:0] $end
$var wire 1 & arg_vld $end
$var wire 32 B" b [31:0] $end
$var wire 1 C" overflow $end
$var wire 1 > res_vld $end
$var wire 33 D" tmp [32:0] $end
$var wire 32 E" res [31:0] $end
$var parameter 32 F" ARG_WIDTH $end
$var parameter 32 G" RES_WIDTH $end
$upscope $end
$scope module sub2 $end
$var wire 32 H" a [31:0] $end
$var wire 1 D arg_vld $end
$var wire 32 I" b [31:0] $end
$var wire 1 J" overflow $end
$var wire 1 < res_vld $end
$var wire 33 K" tmp [32:0] $end
$var wire 32 L" res [31:0] $end
$var parameter 32 M" ARG_WIDTH $end
$var parameter 32 N" RES_WIDTH $end
$upscope $end
$upscope $end
$scope task reset $end
$upscope $end
$upscope $end
$enddefinitions $end
$comment Show the parameter values. $end
$dumpall
b100000 N"
b100000 M"
b100000 G"
b100000 F"
b100000 @"
b100000 ?"
b1 :"
b100000 8"
b1 6"
b100000 4"
b1 2"
b100000 0"
b1 ."
b100000 ,"
b100000 *"
b100000 )"
b100000 #"
b100000 ""
b10 w
b100000 v
b10 u
b11 t
1n
b100000 m
b1 l
b10 k
b100000 h
b100000 g
b100000 d
b100000 c
b100000 ]
b100000 \
b100000 [
b100000 Z
b100000 Y
b100000 X
b100000 W
b100000 V
b100000 U
b100000 T
b100000 #
$end
#0
$dumpvars
bx L"
bx K"
xJ"
bx I"
bx H"
bx E"
bx D"
xC"
bx B"
bx A"
x>"
bx00 ="
bx00 <"
bx ;"
bx 9"
bx 7"
bx 5"
bx 3"
bx 1"
bx /"
bx -"
bx +"
bx ("
x'"
bx &"
bx %"
bx $"
x!"
bx ~
bx }
bx |
b11 {
bx z
bx y
xx
bx00 s
bx r
xq
xp
xo
bx j
bx i
bx f
bx e
bx b
bx a
bx `
x_
b1 ^
bx S
xR
bx Q
xP
bx O
xN
bx M
xL
bx K
bx J
bx I
xH
bx G
0F
bx E
xD
bx C
xB
bx00 A
0@
bx ?
0>
bx =
x<
bx ;
bx :
bx 9
bx 8
bx 7
b0 6
b0 5
b0 4
b0 3
b0 2
01
x0
bx /
bx .
bx -
bx ,
1+
bx *
bx )
bx (
bx '
0&
bx %
bx $
bx "
x!
$end
#5
0+
#10
b1 3
0P
0H
1+
#15
0+
#20
0B
0R
b10 3
1+
#25
0+
#30
0q
0p
0o
b0 z
b0 y
0x
10
b11 3
0L
0<
0D
1+
#35
0+
#40
0!
0N
b100 3
11
1+
#45
0+
#50
b101 3
1+
#55
0+
#60
0>"
b0 A
b0 s
b0 ="
0C"
b0 <"
0!"
b0 G
b0 ~
b0 +"
b0 ?
b0 j
b0 E"
b0 .
1F
1@
1>
1&
b0 ,
b0 :
b0 ;"
b0 }
b0 )
b0 9
b0 |
b0 D"
b0 '
b0 8
b0 B"
b0 $
b0 7
b0 A"
b110 3
00
b101 2
b0 /
b0 -
b0 *
b0 (
b0 %
b1 6
b10000000000000000000000000000011 5
1+
#65
0+
#70
0_
b10000 A
b10000 s
b10000 ="
b1 Q
b1 a
b1 /"
b10000 <"
b1001 G
b1001 ~
b1001 +"
b11111111111111111111111111111111 ?
b11111111111111111111111111111111 j
b11111111111111111111111111111111 E"
b111 3
b0 J
b0 r
b0 I"
b0 K
b0 i
b0 $"
b1 `
b0 I
b0 b
b0 -"
1P
1H
b11111111111111111111111111110011 .
b100 ,
b100 :
b100 ;"
0!"
b1001 }
b11 )
b11 9
b11 |
b10 '
b10 8
b10 B"
b111111111111111111111111111111111 D"
b1 $
b1 7
b1 A"
1F
1@
1>
1&
1q
b1 z
b11111111111111111111111111110011 /
b100 -
b11 *
b10 (
b1 %
b10 6
1+
#75
0+
#80
b11000 A
b11000 s
b11000 ="
b11000 <"
b10000000000000000000000000000000 G
b10000000000000000000000000000000 ~
b10000000000000000000000000000000 +"
b0 ?
b0 j
b0 E"
b1010 Q
b1010 a
b1010 /"
0'"
b0 C
b0 &"
b0 3"
b11111111111111111111111111110100 .
b110 ,
b110 :
b110 ;"
1!"
b1111111111111111111111111111111010000000000000000000000000000000 }
b10000000000000000000000000000000 )
b10000000000000000000000000000000 9
b10000000000000000000000000000000 |
b110 '
b110 8
b110 B"
b0 D"
b110 $
b110 7
b110 A"
1F
1@
1>
1&
b1010 `
b1001 I
b1001 b
b1001 -"
1B
1R
b0 %"
b1 S
b1 ("
b1 1"
b1000 3
b10 z
1o
0q
b11111111111111111111111111110100 /
b110 -
b10000000000000000000000000000000 *
b110 (
b110 %
b11 6
1+
#85
0+
#90
0J"
b0 M
b0 e
b0 7"
b0 =
b0 f
b0 L"
b10000000000000000000000000000001 Q
b10000000000000000000000000000001 a
b10000000000000000000000000000001 /"
b1 ?
b1 j
b1 E"
b11111111111111111111111111110110 C
b11111111111111111111111111110110 &"
b11111111111111111111111111110110 3"
b1001 3
b0 K"
b0 E
b0 5"
b0 H"
1L
1<
1D
b1010 S
b1010 ("
b1010 1"
b110000000000000000000000000000001 `
b10000000000000000000000000000000 I
b10000000000000000000000000000000 b
b10000000000000000000000000000000 -"
b111111111111111111111111110100 .
b0 '
b0 8
b0 B"
b1 D"
b1 $
b1 7
b1 A"
1F
1@
1>
1&
1q
0'"
b1111111111111111111111111111111111111111111111111111111111110110 %"
b11111111111111111111111111111111 K
b11111111111111111111111111111111 i
b11111111111111111111111111111111 $"
1p
b0 z
1x
b111111111111111111111111110100 /
b0 (
b1 %
b100 6
1+
#95
0+
#100
b1010000 A
b1010000 s
b1010000 ="
b11111111111111111111111111110011 M
b11111111111111111111111111110011 e
b11111111111111111111111111110011 7"
b1010000 <"
0!"
b10110001 G
b10110001 ~
b10110001 +"
b111001 ?
b111001 j
b111001 E"
b11111111111111111111111111100110 =
b11111111111111111111111111100110 f
b11111111111111111111111111100110 L"
b0 C
b0 &"
b0 3"
b1001110101001 .
b10100 ,
b10100 :
b10100 ;"
b10110001 }
b111011 )
b111011 9
b111011 |
b11011 '
b11011 8
b11011 B"
b111001 D"
b1010100 $
b1010100 7
b1010100 A"
1F
1@
1>
1&
b10000000000000000000000000000001 S
b10000000000000000000000000000001 ("
b10000000000000000000000000000001 1"
b11111111111111111111111111110110 E
b11111111111111111111111111110110 5"
b11111111111111111111111111110110 H"
1!
1N
b0 "
b0 ;
b0 O
b0 9"
b1010 3
b111111111111111111111111111100110 K"
b10000 J
b10000 r
b10000 I"
b1 y
b1 z
0'"
b0 %"
b0 K
b0 i
b0 $"
0p
0q
b1001110101001 /
b10100 -
b111011 *
b11011 (
b1010100 %
b101 6
1+
#105
0+
#110
1>"
b11111111111111111111111000110100 A
b11111111111111111111111000110100 s
b11111111111111111111111000110100 ="
b11111111111111111111111111110100 M
b11111111111111111111111111110100 e
b11111111111111111111111111110100 7"
b10110010 Q
b10110010 a
b10110010 /"
b1111111111111111111111111000110100 <"
b11111111111111111111111100101000 G
b11111111111111111111111100101000 ~
b11111111111111111111111100101000 +"
b11111111111111111111111111001011 ?
b11111111111111111111111111001011 j
b11111111111111111111111111001011 E"
b10000000000000000000000000000001 C
b10000000000000000000000000000001 &"
b10000000000000000000000000000001 3"
b11111111111111111111111111101000 =
b11111111111111111111111111101000 f
b11111111111111111111111111101000 L"
b1011 3
b11111111111111111111111111110011 "
b11111111111111111111111111110011 ;
b11111111111111111111111111110011 O
b11111111111111111111111111110011 9"
b0 E
b0 5"
b0 H"
b10110010 `
b10110001 I
b10110001 b
b10110001 -"
b11111111111111111111111110001101 ,
b11111111111111111111111110001101 :
b11111111111111111111111110001101 ;"
0!"
b1111111111111111111111111111111111111111111111111111111100101000 }
b11111111111111111111111110111000 )
b11111111111111111111111110111000 9
b11111111111111111111111110111000 |
b1110 '
b1110 8
b1110 B"
b111111111111111111111111111001011 D"
b11111111111111111111111111011001 $
b11111111111111111111111111011001 7
b11111111111111111111111111011001 A"
1F
1@
1>
1&
1q
0'"
b1111111111111111111111111111111110000000000000000000000000000001 %"
b1 K
b1 i
b1 $"
1p
b10 z
b111111111111111111111111111101000 K"
b11000 J
b11000 r
b11000 I"
b10 y
b1011100100111 .
b1011100100111 /
b11111111111111111111111110001101 -
b11111111111111111111111110111000 *
b1110 (
b11111111111111111111111111011001 %
b110 6
1+
#115
0+
#120
0>"
b100 A
b100 s
b100 ="
1J"
b111111111111111111111111110100 M
b111111111111111111111111110100 e
b111111111111111111111111110100 7"
b100 <"
b100000010 G
b100000010 ~
b100000010 +"
b11111111111111111111111110111011 ?
b11111111111111111111111110111011 j
b11111111111111111111111110111011 E"
b11111111111111111111111100101001 Q
b11111111111111111111111100101001 a
b11111111111111111111111100101001 /"
b1111111111111111111111111101001 =
b1111111111111111111111111101001 f
b1111111111111111111111111101001 L"
b10011110100010 C
b10011110100010 &"
b10011110100010 3"
b1 ,
b1 :
b1 ;"
0!"
b100000010 }
b1010110 )
b1010110 9
b1010110 |
b1000100 '
b1000100 8
b1000100 B"
b111111111111111111111111110111011 D"
b11111111111111111111111111111111 $
b11111111111111111111111111111111 7
b11111111111111111111111111111111 A"
1F
1@
1>
1&
b111111111111111111111111100101001 `
b11111111111111111111111100101000 I
b11111111111111111111111100101000 b
b11111111111111111111111100101000 -"
b10110010 S
b10110010 ("
b10110010 1"
b101111111111111111111111111101001 K"
b10000000000000000000000000000001 E
b10000000000000000000000000000001 5"
b10000000000000000000000000000001 H"
b11111111111111111111111111110100 "
b11111111111111111111111111110100 ;
b11111111111111111111111111110100 O
b11111111111111111111111111110100 9"
b1100 3
b0 y
b0 z
0'"
b10011110100010 %"
b111001 K
b111001 i
b111001 $"
0p
0q
b11111111111111111101110100010110 /
b1 -
b1010110 *
b1000100 (
b11111111111111111111111111111111 %
b111 6
b11111111111111111101110100010110 .
1+
#125
0+
